odoo/addons/mgmtsystem_nonconformity_mrp/README.rst
odoo/addons/mgmtsystem_nonconformity_mrp/__init__.py
odoo/addons/mgmtsystem_nonconformity_mrp/__manifest__.py
odoo/addons/mgmtsystem_nonconformity_mrp/i18n/es.po
odoo/addons/mgmtsystem_nonconformity_mrp/i18n/fr.po
odoo/addons/mgmtsystem_nonconformity_mrp/i18n/it.po
odoo/addons/mgmtsystem_nonconformity_mrp/i18n/mgmtsystem_nonconformity_mrp.pot
odoo/addons/mgmtsystem_nonconformity_mrp/models/__init__.py
odoo/addons/mgmtsystem_nonconformity_mrp/models/mgmtsystem_nonconformity_mrp.py
odoo/addons/mgmtsystem_nonconformity_mrp/readme/CONFIGURE.md
odoo/addons/mgmtsystem_nonconformity_mrp/readme/CONTRIBUTORS.md
odoo/addons/mgmtsystem_nonconformity_mrp/readme/DESCRIPTION.md
odoo/addons/mgmtsystem_nonconformity_mrp/readme/HISTORY.md
odoo/addons/mgmtsystem_nonconformity_mrp/readme/INSTALL.md
odoo/addons/mgmtsystem_nonconformity_mrp/readme/ROADMAP.md
odoo/addons/mgmtsystem_nonconformity_mrp/readme/USAGE.md
odoo/addons/mgmtsystem_nonconformity_mrp/static/description/icon.png
odoo/addons/mgmtsystem_nonconformity_mrp/static/description/index.html
odoo/addons/mgmtsystem_nonconformity_mrp/views/mgmtsystem_nonconformity_views.xml
odoo_addon_mgmtsystem_nonconformity_mrp-18.0.1.0.0.2.dist-info/METADATA
odoo_addon_mgmtsystem_nonconformity_mrp-18.0.1.0.0.2.dist-info/WHEEL
odoo_addon_mgmtsystem_nonconformity_mrp-18.0.1.0.0.2.dist-info/top_level.txt
odoo_addon_mgmtsystem_nonconformity_mrp-18.0.1.0.0.2.dist-info/RECORD
